rs_dssp/__init__.py
rs_dssp/__init__.pyi
rs_dssp/__pycache__/__init__.cpython-311.pyc
rs_dssp/__pycache__/cli.cpython-311.pyc
rs_dssp/cli.py
rs_dssp/rs_dssp.cpython-311-x86_64-linux-gnu.so
rs_dssp-0.2.1.dist-info/METADATA
rs_dssp-0.2.1.dist-info/WHEEL
rs_dssp-0.2.1.dist-info/entry_points.txt
rs_dssp-0.2.1.dist-info/RECORD
