Metadata-Version: 2.4
Name: rs-dssp
Version: 0.2.1
Classifier: Development Status :: 4 - Beta
Classifier: Intended Audience :: Science/Research
Classifier: License :: OSI Approved :: MIT License
Classifier: License :: OSI Approved :: Apache Software License
Classifier: Programming Language :: Python :: 3
Classifier: Programming Language :: Python :: 3.9
Classifier: Programming Language :: Python :: 3.10
Classifier: Programming Language :: Python :: 3.11
Classifier: Programming Language :: Python :: 3.12
Classifier: Programming Language :: Python :: 3.13
Classifier: Programming Language :: Rust
Classifier: Topic :: Scientific/Engineering :: Bio-Informatics
Requires-Dist: numpy>=1.20
Requires-Dist: typer>=0.9
Requires-Dist: rich>=13.0
Requires-Dist: pytest ; extra == 'dev'
Requires-Dist: pytest-benchmark ; extra == 'dev'
Requires-Dist: biopython ; extra == 'dev'
Provides-Extra: dev
Summary: High-performance DSSP implementation in Rust with Python bindings
Keywords: protein,secondary-structure,dssp,bioinformatics
Author: cheng_shizhuo
License: MIT OR Apache-2.0
Requires-Python: >=3.9
